anci/__init__.py
anci/_action.py
anci/_arg.py
anci/_main.py
anci/_tree.py
anci/_types.py
anci/py.typed
anci/typing.py
anci/handlers/__init__.py
anci/handlers/_annotated.py
anci/handlers/_type.py
anci-0.1.5.dist-info/METADATA
anci-0.1.5.dist-info/WHEEL
anci-0.1.5.dist-info/licenses/LICENSE
anci-0.1.5.dist-info/RECORD
