Metadata-Version: 2.4
Name: anci
Version: 0.1.5
Summary: Annotated command-line interfaces in Python
Author-email: Tom Ouellette <touellette112@gmail.com>
License-File: LICENSE
Requires-Python: >=3.11
Requires-Dist: annotated-types>=0.7.0
Provides-Extra: tests
Requires-Dist: pytest; extra == 'tests'
